CONTRIBUTING.md
LICENSE
MANIFEST.in
README.md
setup.cfg
setup.py
ose_workbench_platform.egg-info/PKG-INFO
ose_workbench_platform.egg-info/SOURCES.txt
ose_workbench_platform.egg-info/dependency_links.txt
ose_workbench_platform.egg-info/entry_points.txt
ose_workbench_platform.egg-info/requires.txt
ose_workbench_platform.egg-info/top_level.txt
osewb/.flake8
osewb/.mustache
osewb/.mypy.ini
osewb/.pycodestyle
osewb/__init__.py
osewb/_version.py
osewb/check_for_executable_in_path.py
osewb/execute_command.py
osewb/find_base_package.py
osewb/handle_browse_command.py
osewb/handle_build_command.py
osewb/handle_docs_command.py
osewb/handle_editor_config_command.py
osewb/handle_lint_command.py
osewb/handle_make_component_command.py
osewb/handle_make_workbench_command.py
osewb/handle_test_command.py
osewb/osewb.py
osewb/part_screenshot.py
osewb/cookiecutter_ose_workbench/cookiecutter.json
osewb/cookiecutter_ose_workbench/{{ cookiecutter.repo_name }}/.env
osewb/cookiecutter_ose_workbench/{{ cookiecutter.repo_name }}/.gitignore
osewb/cookiecutter_ose_workbench/{{ cookiecutter.repo_name }}/.readthedocs.yml
osewb/cookiecutter_ose_workbench/{{ cookiecutter.repo_name }}/.travis.yml
osewb/cookiecutter_ose_workbench/{{ cookiecutter.repo_name }}/CONTRIBUTING.md
osewb/cookiecutter_ose_workbench/{{ cookiecutter.repo_name }}/LICENSE
osewb/cookiecutter_ose_workbench/{{ cookiecutter.repo_name }}/MANIFEST.in
osewb/cookiecutter_ose_workbench/{{ cookiecutter.repo_name }}/README.md
osewb/cookiecutter_ose_workbench/{{ cookiecutter.repo_name }}/environment.yml
osewb/cookiecutter_ose_workbench/{{ cookiecutter.repo_name }}/setup.py
osewb/cookiecutter_ose_workbench/{{ cookiecutter.repo_name }}/.vscode/extensions.json
osewb/cookiecutter_ose_workbench/{{ cookiecutter.repo_name }}/docs/conf.py
osewb/cookiecutter_ose_workbench/{{ cookiecutter.repo_name }}/docs/index.rst
osewb/cookiecutter_ose_workbench/{{ cookiecutter.repo_name }}/freecad/{{ cookiecutter.base_package }}/__init__.py
osewb/cookiecutter_ose_workbench/{{ cookiecutter.repo_name }}/freecad/{{ cookiecutter.base_package }}/init_gui.py
osewb/cookiecutter_ose_workbench/{{ cookiecutter.repo_name }}/freecad/{{ cookiecutter.base_package }}/{{ cookiecutter.command_registry_filename }}.py
