Metadata-Version: 2.1
Name: ose-workbench-platform
Version: 0.1.0
Summary: Common platform for developing Open Source Ecology (OSE) workbenches.
Home-page: https://github.com/gbroques/ose-workbench-platform
Author: G Roques
License: UNKNOWN
Platform: UNKNOWN
Classifier: License :: OSI Approved :: GNU Lesser General Public License v2 or later (LGPLv2+)
Classifier: Programming Language :: Python :: 3 :: Only
